server.py
simple_math_server-0.1.1.dist-info/METADATA
simple_math_server-0.1.1.dist-info/WHEEL
simple_math_server-0.1.1.dist-info/entry_points.txt
simple_math_server-0.1.1.dist-info/top_level.txt
simple_math_server-0.1.1.dist-info/RECORD
