Metadata-Version: 2.4
Name: simple-math-server
Version: 0.1.1
Summary: Add your description here
Requires-Python: >=3.13
Requires-Dist: mcp>=1.15.0
